<?xml version="1.0"?>
<network xmlns="http://sndlib.zib.de/network" version="1.0">
 <meta>
  <granularity>5min</granularity>
  <time>20040422-0020</time>
  <unit>MBITPERSEC</unit>
  <origin>Yin Zhang, http://userweb.cs.utexas.edu/~yzhang/research/AbileneTM/</origin>
 </meta>
 <networkStructure>
  <nodes coordinatesType="geographical">
   <node id="ATLAM5">
    <coordinates>
     <x>-84.383300</x>
     <y>33.750000</y>
    </coordinates>
   </node>
   <node id="ATLAng">
    <coordinates>
     <x>-85.5</x>
     <y>34.5</y>
    </coordinates>
   </node>
   <node id="CHINng">
    <coordinates>
     <x>-87.616700</x>
     <y>41.833300</y>
    </coordinates>
   </node>
   <node id="DNVRng">
    <coordinates>
     <x>-105.000000</x>
     <y>40.750000</y>
    </coordinates>
   </node>
   <node id="HSTNng">
    <coordinates>
     <x>-95.517364</x>
     <y>29.770031</y>
    </coordinates>
   </node>
   <node id="IPLSng">
    <coordinates>
     <x>-86.159535</x>
     <y>39.780622</y>
    </coordinates>
   </node>
   <node id="KSCYng">
    <coordinates>
     <x>-96.596704</x>
     <y>38.961694</y>
    </coordinates>
   </node>
   <node id="LOSAng">
    <coordinates>
     <x>-118.250000</x>
     <y>34.050000</y>
    </coordinates>
   </node>
   <node id="NYCMng">
    <coordinates>
     <x>-73.966700</x>
     <y>40.783300</y>
    </coordinates>
   </node>
   <node id="SNVAng">
    <coordinates>
     <x>-122.02553</x>
     <y>37.38575</y>
    </coordinates>
   </node>
   <node id="STTLng">
    <coordinates>
     <x>-122.300000</x>
     <y>47.600000</y>
    </coordinates>
   </node>
   <node id="WASHng">
    <coordinates>
     <x>-77.026842</x>
     <y>38.897303</y>
    </coordinates>
   </node>
  </nodes>
  <links>
  </links>
 </networkStructure>
 <demands>
  <demand id="ATLAM5_ATLAng">
   <source>ATLAM5</source>
   <target>ATLAng</target>
   <demandValue> 0.485048 </demandValue>
  </demand>
  <demand id="ATLAM5_CHINng">
   <source>ATLAM5</source>
   <target>CHINng</target>
   <demandValue> 0.530064 </demandValue>
  </demand>
  <demand id="ATLAM5_HSTNng">
   <source>ATLAM5</source>
   <target>HSTNng</target>
   <demandValue> 1.021547 </demandValue>
  </demand>
  <demand id="ATLAM5_IPLSng">
   <source>ATLAM5</source>
   <target>IPLSng</target>
   <demandValue> 0.729333 </demandValue>
  </demand>
  <demand id="ATLAM5_KSCYng">
   <source>ATLAM5</source>
   <target>KSCYng</target>
   <demandValue> 0.295971 </demandValue>
  </demand>
  <demand id="ATLAM5_NYCMng">
   <source>ATLAM5</source>
   <target>NYCMng</target>
   <demandValue> 0.358840 </demandValue>
  </demand>
  <demand id="ATLAM5_WASHng">
   <source>ATLAM5</source>
   <target>WASHng</target>
   <demandValue> 0.865200 </demandValue>
  </demand>
  <demand id="ATLAng_CHINng">
   <source>ATLAng</source>
   <target>CHINng</target>
   <demandValue> 50.282531 </demandValue>
  </demand>
  <demand id="ATLAng_HSTNng">
   <source>ATLAng</source>
   <target>HSTNng</target>
   <demandValue> 53.863221 </demandValue>
  </demand>
  <demand id="ATLAng_IPLSng">
   <source>ATLAng</source>
   <target>IPLSng</target>
   <demandValue> 50.180464 </demandValue>
  </demand>
  <demand id="ATLAng_KSCYng">
   <source>ATLAng</source>
   <target>KSCYng</target>
   <demandValue> 8.301408 </demandValue>
  </demand>
  <demand id="ATLAng_LOSAng">
   <source>ATLAng</source>
   <target>LOSAng</target>
   <demandValue> 0.446997 </demandValue>
  </demand>
  <demand id="ATLAng_NYCMng">
   <source>ATLAng</source>
   <target>NYCMng</target>
   <demandValue> 25.387589 </demandValue>
  </demand>
  <demand id="ATLAng_SNVAng">
   <source>ATLAng</source>
   <target>SNVAng</target>
   <demandValue> 0.465099 </demandValue>
  </demand>
  <demand id="ATLAng_STTLng">
   <source>ATLAng</source>
   <target>STTLng</target>
   <demandValue> 0.646120 </demandValue>
  </demand>
  <demand id="ATLAng_WASHng">
   <source>ATLAng</source>
   <target>WASHng</target>
   <demandValue> 53.348189 </demandValue>
  </demand>
  <demand id="CHINng_ATLAng">
   <source>CHINng</source>
   <target>ATLAng</target>
   <demandValue> 39.282981 </demandValue>
  </demand>
  <demand id="CHINng_DNVRng">
   <source>CHINng</source>
   <target>DNVRng</target>
   <demandValue> 22.953664 </demandValue>
  </demand>
  <demand id="CHINng_HSTNng">
   <source>CHINng</source>
   <target>HSTNng</target>
   <demandValue> 151.316456 </demandValue>
  </demand>
  <demand id="CHINng_IPLSng">
   <source>CHINng</source>
   <target>IPLSng</target>
   <demandValue> 102.268752 </demandValue>
  </demand>
  <demand id="CHINng_KSCYng">
   <source>CHINng</source>
   <target>KSCYng</target>
   <demandValue> 30.510128 </demandValue>
  </demand>
  <demand id="CHINng_LOSAng">
   <source>CHINng</source>
   <target>LOSAng</target>
   <demandValue> 0.337683 </demandValue>
  </demand>
  <demand id="CHINng_NYCMng">
   <source>CHINng</source>
   <target>NYCMng</target>
   <demandValue> 49.505933 </demandValue>
  </demand>
  <demand id="CHINng_SNVAng">
   <source>CHINng</source>
   <target>SNVAng</target>
   <demandValue> 0.059307 </demandValue>
  </demand>
  <demand id="CHINng_STTLng">
   <source>CHINng</source>
   <target>STTLng</target>
   <demandValue> 1.741280 </demandValue>
  </demand>
  <demand id="CHINng_WASHng">
   <source>CHINng</source>
   <target>WASHng</target>
   <demandValue> 57.218443 </demandValue>
  </demand>
  <demand id="DNVRng_ATLAng">
   <source>DNVRng</source>
   <target>ATLAng</target>
   <demandValue> 10.000336 </demandValue>
  </demand>
  <demand id="DNVRng_CHINng">
   <source>DNVRng</source>
   <target>CHINng</target>
   <demandValue> 54.871563 </demandValue>
  </demand>
  <demand id="DNVRng_HSTNng">
   <source>DNVRng</source>
   <target>HSTNng</target>
   <demandValue> 49.598512 </demandValue>
  </demand>
  <demand id="DNVRng_IPLSng">
   <source>DNVRng</source>
   <target>IPLSng</target>
   <demandValue> 32.337707 </demandValue>
  </demand>
  <demand id="DNVRng_KSCYng">
   <source>DNVRng</source>
   <target>KSCYng</target>
   <demandValue> 7.140112 </demandValue>
  </demand>
  <demand id="DNVRng_NYCMng">
   <source>DNVRng</source>
   <target>NYCMng</target>
   <demandValue> 22.270395 </demandValue>
  </demand>
  <demand id="DNVRng_SNVAng">
   <source>DNVRng</source>
   <target>SNVAng</target>
   <demandValue> 5.733072 </demandValue>
  </demand>
  <demand id="DNVRng_STTLng">
   <source>DNVRng</source>
   <target>STTLng</target>
   <demandValue> 0.943549 </demandValue>
  </demand>
  <demand id="DNVRng_WASHng">
   <source>DNVRng</source>
   <target>WASHng</target>
   <demandValue> 34.267029 </demandValue>
  </demand>
  <demand id="HSTNng_ATLAng">
   <source>HSTNng</source>
   <target>ATLAng</target>
   <demandValue> 48.791021 </demandValue>
  </demand>
  <demand id="HSTNng_CHINng">
   <source>HSTNng</source>
   <target>CHINng</target>
   <demandValue> 0.577027 </demandValue>
  </demand>
  <demand id="HSTNng_IPLSng">
   <source>HSTNng</source>
   <target>IPLSng</target>
   <demandValue> 0.069061 </demandValue>
  </demand>
  <demand id="HSTNng_KSCYng">
   <source>HSTNng</source>
   <target>KSCYng</target>
   <demandValue> 0.109643 </demandValue>
  </demand>
  <demand id="HSTNng_NYCMng">
   <source>HSTNng</source>
   <target>NYCMng</target>
   <demandValue> 8.425611 </demandValue>
  </demand>
  <demand id="HSTNng_STTLng">
   <source>HSTNng</source>
   <target>STTLng</target>
   <demandValue> 0.410165 </demandValue>
  </demand>
  <demand id="HSTNng_WASHng">
   <source>HSTNng</source>
   <target>WASHng</target>
   <demandValue> 152.356323 </demandValue>
  </demand>
  <demand id="IPLSng_ATLAng">
   <source>IPLSng</source>
   <target>ATLAng</target>
   <demandValue> 18.926659 </demandValue>
  </demand>
  <demand id="IPLSng_CHINng">
   <source>IPLSng</source>
   <target>CHINng</target>
   <demandValue> 203.883248 </demandValue>
  </demand>
  <demand id="IPLSng_DNVRng">
   <source>IPLSng</source>
   <target>DNVRng</target>
   <demandValue> 51.109152 </demandValue>
  </demand>
  <demand id="IPLSng_HSTNng">
   <source>IPLSng</source>
   <target>HSTNng</target>
   <demandValue> 94.514211 </demandValue>
  </demand>
  <demand id="IPLSng_KSCYng">
   <source>IPLSng</source>
   <target>KSCYng</target>
   <demandValue> 9.370824 </demandValue>
  </demand>
  <demand id="IPLSng_LOSAng">
   <source>IPLSng</source>
   <target>LOSAng</target>
   <demandValue> 0.053333 </demandValue>
  </demand>
  <demand id="IPLSng_NYCMng">
   <source>IPLSng</source>
   <target>NYCMng</target>
   <demandValue> 94.339115 </demandValue>
  </demand>
  <demand id="IPLSng_SNVAng">
   <source>IPLSng</source>
   <target>SNVAng</target>
   <demandValue> 0.366392 </demandValue>
  </demand>
  <demand id="IPLSng_STTLng">
   <source>IPLSng</source>
   <target>STTLng</target>
   <demandValue> 0.903299 </demandValue>
  </demand>
  <demand id="IPLSng_WASHng">
   <source>IPLSng</source>
   <target>WASHng</target>
   <demandValue> 65.326493 </demandValue>
  </demand>
  <demand id="KSCYng_ATLAng">
   <source>KSCYng</source>
   <target>ATLAng</target>
   <demandValue> 10.102784 </demandValue>
  </demand>
  <demand id="KSCYng_CHINng">
   <source>KSCYng</source>
   <target>CHINng</target>
   <demandValue> 32.231837 </demandValue>
  </demand>
  <demand id="KSCYng_DNVRng">
   <source>KSCYng</source>
   <target>DNVRng</target>
   <demandValue> 6.811600 </demandValue>
  </demand>
  <demand id="KSCYng_HSTNng">
   <source>KSCYng</source>
   <target>HSTNng</target>
   <demandValue> 19.789507 </demandValue>
  </demand>
  <demand id="KSCYng_IPLSng">
   <source>KSCYng</source>
   <target>IPLSng</target>
   <demandValue> 21.196811 </demandValue>
  </demand>
  <demand id="KSCYng_LOSAng">
   <source>KSCYng</source>
   <target>LOSAng</target>
   <demandValue> 0.128480 </demandValue>
  </demand>
  <demand id="KSCYng_NYCMng">
   <source>KSCYng</source>
   <target>NYCMng</target>
   <demandValue> 11.073925 </demandValue>
  </demand>
  <demand id="KSCYng_STTLng">
   <source>KSCYng</source>
   <target>STTLng</target>
   <demandValue> 0.213333 </demandValue>
  </demand>
  <demand id="KSCYng_WASHng">
   <source>KSCYng</source>
   <target>WASHng</target>
   <demandValue> 18.562739 </demandValue>
  </demand>
  <demand id="LOSAng_ATLAng">
   <source>LOSAng</source>
   <target>ATLAng</target>
   <demandValue> 38.107427 </demandValue>
  </demand>
  <demand id="LOSAng_CHINng">
   <source>LOSAng</source>
   <target>CHINng</target>
   <demandValue> 20.306805 </demandValue>
  </demand>
  <demand id="LOSAng_DNVRng">
   <source>LOSAng</source>
   <target>DNVRng</target>
   <demandValue> 23.348536 </demandValue>
  </demand>
  <demand id="LOSAng_HSTNng">
   <source>LOSAng</source>
   <target>HSTNng</target>
   <demandValue> 255.900365 </demandValue>
  </demand>
  <demand id="LOSAng_IPLSng">
   <source>LOSAng</source>
   <target>IPLSng</target>
   <demandValue> 0.467547 </demandValue>
  </demand>
  <demand id="LOSAng_KSCYng">
   <source>LOSAng</source>
   <target>KSCYng</target>
   <demandValue> 1.281379 </demandValue>
  </demand>
  <demand id="LOSAng_NYCMng">
   <source>LOSAng</source>
   <target>NYCMng</target>
   <demandValue> 97.445701 </demandValue>
  </demand>
  <demand id="LOSAng_SNVAng">
   <source>LOSAng</source>
   <target>SNVAng</target>
   <demandValue> 11.596435 </demandValue>
  </demand>
  <demand id="LOSAng_STTLng">
   <source>LOSAng</source>
   <target>STTLng</target>
   <demandValue> 43.927056 </demandValue>
  </demand>
  <demand id="LOSAng_WASHng">
   <source>LOSAng</source>
   <target>WASHng</target>
   <demandValue> 136.895539 </demandValue>
  </demand>
  <demand id="NYCMng_ATLAng">
   <source>NYCMng</source>
   <target>ATLAng</target>
   <demandValue> 57.298909 </demandValue>
  </demand>
  <demand id="NYCMng_CHINng">
   <source>NYCMng</source>
   <target>CHINng</target>
   <demandValue> 108.832989 </demandValue>
  </demand>
  <demand id="NYCMng_DNVRng">
   <source>NYCMng</source>
   <target>DNVRng</target>
   <demandValue> 47.250995 </demandValue>
  </demand>
  <demand id="NYCMng_HSTNng">
   <source>NYCMng</source>
   <target>HSTNng</target>
   <demandValue> 195.571648 </demandValue>
  </demand>
  <demand id="NYCMng_IPLSng">
   <source>NYCMng</source>
   <target>IPLSng</target>
   <demandValue> 100.556504 </demandValue>
  </demand>
  <demand id="NYCMng_KSCYng">
   <source>NYCMng</source>
   <target>KSCYng</target>
   <demandValue> 20.336883 </demandValue>
  </demand>
  <demand id="NYCMng_LOSAng">
   <source>NYCMng</source>
   <target>LOSAng</target>
   <demandValue> 2.999411 </demandValue>
  </demand>
  <demand id="NYCMng_SNVAng">
   <source>NYCMng</source>
   <target>SNVAng</target>
   <demandValue> 0.253819 </demandValue>
  </demand>
  <demand id="NYCMng_STTLng">
   <source>NYCMng</source>
   <target>STTLng</target>
   <demandValue> 5.768720 </demandValue>
  </demand>
  <demand id="NYCMng_WASHng">
   <source>NYCMng</source>
   <target>WASHng</target>
   <demandValue> 169.677619 </demandValue>
  </demand>
  <demand id="SNVAng_ATLAng">
   <source>SNVAng</source>
   <target>ATLAng</target>
   <demandValue> 1.334899 </demandValue>
  </demand>
  <demand id="SNVAng_CHINng">
   <source>SNVAng</source>
   <target>CHINng</target>
   <demandValue> 0.361789 </demandValue>
  </demand>
  <demand id="SNVAng_DNVRng">
   <source>SNVAng</source>
   <target>DNVRng</target>
   <demandValue> 1.429821 </demandValue>
  </demand>
  <demand id="SNVAng_HSTNng">
   <source>SNVAng</source>
   <target>HSTNng</target>
   <demandValue> 5.728808 </demandValue>
  </demand>
  <demand id="SNVAng_IPLSng">
   <source>SNVAng</source>
   <target>IPLSng</target>
   <demandValue> 0.072851 </demandValue>
  </demand>
  <demand id="SNVAng_KSCYng">
   <source>SNVAng</source>
   <target>KSCYng</target>
   <demandValue> 0.709389 </demandValue>
  </demand>
  <demand id="SNVAng_LOSAng">
   <source>SNVAng</source>
   <target>LOSAng</target>
   <demandValue> 53.757731 </demandValue>
  </demand>
  <demand id="SNVAng_NYCMng">
   <source>SNVAng</source>
   <target>NYCMng</target>
   <demandValue> 5.211469 </demandValue>
  </demand>
  <demand id="SNVAng_STTLng">
   <source>SNVAng</source>
   <target>STTLng</target>
   <demandValue> 31.512440 </demandValue>
  </demand>
  <demand id="SNVAng_WASHng">
   <source>SNVAng</source>
   <target>WASHng</target>
   <demandValue> 3.231552 </demandValue>
  </demand>
  <demand id="STTLng_ATLAng">
   <source>STTLng</source>
   <target>ATLAng</target>
   <demandValue> 17.191216 </demandValue>
  </demand>
  <demand id="STTLng_CHINng">
   <source>STTLng</source>
   <target>CHINng</target>
   <demandValue> 0.702629 </demandValue>
  </demand>
  <demand id="STTLng_DNVRng">
   <source>STTLng</source>
   <target>DNVRng</target>
   <demandValue> 6.562413 </demandValue>
  </demand>
  <demand id="STTLng_HSTNng">
   <source>STTLng</source>
   <target>HSTNng</target>
   <demandValue> 45.899261 </demandValue>
  </demand>
  <demand id="STTLng_KSCYng">
   <source>STTLng</source>
   <target>KSCYng</target>
   <demandValue> 5.494515 </demandValue>
  </demand>
  <demand id="STTLng_LOSAng">
   <source>STTLng</source>
   <target>LOSAng</target>
   <demandValue> 43.843075 </demandValue>
  </demand>
  <demand id="STTLng_NYCMng">
   <source>STTLng</source>
   <target>NYCMng</target>
   <demandValue> 12.668971 </demandValue>
  </demand>
  <demand id="STTLng_SNVAng">
   <source>STTLng</source>
   <target>SNVAng</target>
   <demandValue> 19.461005 </demandValue>
  </demand>
  <demand id="STTLng_WASHng">
   <source>STTLng</source>
   <target>WASHng</target>
   <demandValue> 25.630949 </demandValue>
  </demand>
  <demand id="WASHng_ATLAng">
   <source>WASHng</source>
   <target>ATLAng</target>
   <demandValue> 87.531664 </demandValue>
  </demand>
  <demand id="WASHng_CHINng">
   <source>WASHng</source>
   <target>CHINng</target>
   <demandValue> 100.102749 </demandValue>
  </demand>
  <demand id="WASHng_DNVRng">
   <source>WASHng</source>
   <target>DNVRng</target>
   <demandValue> 0.026667 </demandValue>
  </demand>
  <demand id="WASHng_HSTNng">
   <source>WASHng</source>
   <target>HSTNng</target>
   <demandValue> 263.222419 </demandValue>
  </demand>
  <demand id="WASHng_IPLSng">
   <source>WASHng</source>
   <target>IPLSng</target>
   <demandValue> 66.325853 </demandValue>
  </demand>
  <demand id="WASHng_KSCYng">
   <source>WASHng</source>
   <target>KSCYng</target>
   <demandValue> 17.767272 </demandValue>
  </demand>
  <demand id="WASHng_LOSAng">
   <source>WASHng</source>
   <target>LOSAng</target>
   <demandValue> 0.225179 </demandValue>
  </demand>
  <demand id="WASHng_NYCMng">
   <source>WASHng</source>
   <target>NYCMng</target>
   <demandValue> 206.324795 </demandValue>
  </demand>
  <demand id="WASHng_STTLng">
   <source>WASHng</source>
   <target>STTLng</target>
   <demandValue> 5.632293 </demandValue>
  </demand>
 </demands>
</network>