<?xml version="1.0"?>
<network xmlns="http://sndlib.zib.de/network" version="1.0">
 <meta>
  <granularity>5min</granularity>
  <time>20040712-1320</time>
  <unit>MBITPERSEC</unit>
  <origin>Yin Zhang, http://userweb.cs.utexas.edu/~yzhang/research/AbileneTM/</origin>
 </meta>
 <networkStructure>
  <nodes coordinatesType="geographical">
   <node id="ATLAM5">
    <coordinates>
     <x>-84.383300</x>
     <y>33.750000</y>
    </coordinates>
   </node>
   <node id="ATLAng">
    <coordinates>
     <x>-85.5</x>
     <y>34.5</y>
    </coordinates>
   </node>
   <node id="CHINng">
    <coordinates>
     <x>-87.616700</x>
     <y>41.833300</y>
    </coordinates>
   </node>
   <node id="DNVRng">
    <coordinates>
     <x>-105.000000</x>
     <y>40.750000</y>
    </coordinates>
   </node>
   <node id="HSTNng">
    <coordinates>
     <x>-95.517364</x>
     <y>29.770031</y>
    </coordinates>
   </node>
   <node id="IPLSng">
    <coordinates>
     <x>-86.159535</x>
     <y>39.780622</y>
    </coordinates>
   </node>
   <node id="KSCYng">
    <coordinates>
     <x>-96.596704</x>
     <y>38.961694</y>
    </coordinates>
   </node>
   <node id="LOSAng">
    <coordinates>
     <x>-118.250000</x>
     <y>34.050000</y>
    </coordinates>
   </node>
   <node id="NYCMng">
    <coordinates>
     <x>-73.966700</x>
     <y>40.783300</y>
    </coordinates>
   </node>
   <node id="SNVAng">
    <coordinates>
     <x>-122.02553</x>
     <y>37.38575</y>
    </coordinates>
   </node>
   <node id="STTLng">
    <coordinates>
     <x>-122.300000</x>
     <y>47.600000</y>
    </coordinates>
   </node>
   <node id="WASHng">
    <coordinates>
     <x>-77.026842</x>
     <y>38.897303</y>
    </coordinates>
   </node>
  </nodes>
  <links>
  </links>
 </networkStructure>
 <demands>
  <demand id="ATLAM5_ATLAng">
   <source>ATLAM5</source>
   <target>ATLAng</target>
   <demandValue> 0.503440 </demandValue>
  </demand>
  <demand id="ATLAM5_CHINng">
   <source>ATLAM5</source>
   <target>CHINng</target>
   <demandValue> 0.098853 </demandValue>
  </demand>
  <demand id="ATLAM5_HSTNng">
   <source>ATLAM5</source>
   <target>HSTNng</target>
   <demandValue> 0.074544 </demandValue>
  </demand>
  <demand id="ATLAM5_IPLSng">
   <source>ATLAM5</source>
   <target>IPLSng</target>
   <demandValue> 0.294808 </demandValue>
  </demand>
  <demand id="ATLAM5_LOSAng">
   <source>ATLAM5</source>
   <target>LOSAng</target>
   <demandValue> 0.243168 </demandValue>
  </demand>
  <demand id="ATLAM5_NYCMng">
   <source>ATLAM5</source>
   <target>NYCMng</target>
   <demandValue> 0.134032 </demandValue>
  </demand>
  <demand id="ATLAM5_SNVAng">
   <source>ATLAM5</source>
   <target>SNVAng</target>
   <demandValue> 0.013333 </demandValue>
  </demand>
  <demand id="ATLAM5_WASHng">
   <source>ATLAM5</source>
   <target>WASHng</target>
   <demandValue> 3.127037 </demandValue>
  </demand>
  <demand id="ATLAng_ATLAM5">
   <source>ATLAng</source>
   <target>ATLAM5</target>
   <demandValue> 0.217416 </demandValue>
  </demand>
  <demand id="ATLAng_CHINng">
   <source>ATLAng</source>
   <target>CHINng</target>
   <demandValue> 6.773669 </demandValue>
  </demand>
  <demand id="ATLAng_DNVRng">
   <source>ATLAng</source>
   <target>DNVRng</target>
   <demandValue> 4.669584 </demandValue>
  </demand>
  <demand id="ATLAng_HSTNng">
   <source>ATLAng</source>
   <target>HSTNng</target>
   <demandValue> 1.117968 </demandValue>
  </demand>
  <demand id="ATLAng_IPLSng">
   <source>ATLAng</source>
   <target>IPLSng</target>
   <demandValue> 12.879989 </demandValue>
  </demand>
  <demand id="ATLAng_KSCYng">
   <source>ATLAng</source>
   <target>KSCYng</target>
   <demandValue> 2.487291 </demandValue>
  </demand>
  <demand id="ATLAng_LOSAng">
   <source>ATLAng</source>
   <target>LOSAng</target>
   <demandValue> 13.331379 </demandValue>
  </demand>
  <demand id="ATLAng_NYCMng">
   <source>ATLAng</source>
   <target>NYCMng</target>
   <demandValue> 24.346491 </demandValue>
  </demand>
  <demand id="ATLAng_SNVAng">
   <source>ATLAng</source>
   <target>SNVAng</target>
   <demandValue> 3.345267 </demandValue>
  </demand>
  <demand id="ATLAng_STTLng">
   <source>ATLAng</source>
   <target>STTLng</target>
   <demandValue> 3.481629 </demandValue>
  </demand>
  <demand id="ATLAng_WASHng">
   <source>ATLAng</source>
   <target>WASHng</target>
   <demandValue> 56.999877 </demandValue>
  </demand>
  <demand id="CHINng_ATLAM5">
   <source>CHINng</source>
   <target>ATLAM5</target>
   <demandValue> 0.277413 </demandValue>
  </demand>
  <demand id="CHINng_ATLAng">
   <source>CHINng</source>
   <target>ATLAng</target>
   <demandValue> 16.583181 </demandValue>
  </demand>
  <demand id="CHINng_DNVRng">
   <source>CHINng</source>
   <target>DNVRng</target>
   <demandValue> 9.586629 </demandValue>
  </demand>
  <demand id="CHINng_HSTNng">
   <source>CHINng</source>
   <target>HSTNng</target>
   <demandValue> 30.681555 </demandValue>
  </demand>
  <demand id="CHINng_IPLSng">
   <source>CHINng</source>
   <target>IPLSng</target>
   <demandValue> 24.715152 </demandValue>
  </demand>
  <demand id="CHINng_KSCYng">
   <source>CHINng</source>
   <target>KSCYng</target>
   <demandValue> 26.586709 </demandValue>
  </demand>
  <demand id="CHINng_LOSAng">
   <source>CHINng</source>
   <target>LOSAng</target>
   <demandValue> 24.800805 </demandValue>
  </demand>
  <demand id="CHINng_NYCMng">
   <source>CHINng</source>
   <target>NYCMng</target>
   <demandValue> 11.269797 </demandValue>
  </demand>
  <demand id="CHINng_SNVAng">
   <source>CHINng</source>
   <target>SNVAng</target>
   <demandValue> 0.405256 </demandValue>
  </demand>
  <demand id="CHINng_STTLng">
   <source>CHINng</source>
   <target>STTLng</target>
   <demandValue> 3.806093 </demandValue>
  </demand>
  <demand id="CHINng_WASHng">
   <source>CHINng</source>
   <target>WASHng</target>
   <demandValue> 12.330541 </demandValue>
  </demand>
  <demand id="DNVRng_ATLAM5">
   <source>DNVRng</source>
   <target>ATLAM5</target>
   <demandValue> 0.559691 </demandValue>
  </demand>
  <demand id="DNVRng_ATLAng">
   <source>DNVRng</source>
   <target>ATLAng</target>
   <demandValue> 7.912987 </demandValue>
  </demand>
  <demand id="DNVRng_CHINng">
   <source>DNVRng</source>
   <target>CHINng</target>
   <demandValue> 76.249093 </demandValue>
  </demand>
  <demand id="DNVRng_HSTNng">
   <source>DNVRng</source>
   <target>HSTNng</target>
   <demandValue> 17.234795 </demandValue>
  </demand>
  <demand id="DNVRng_IPLSng">
   <source>DNVRng</source>
   <target>IPLSng</target>
   <demandValue> 41.469685 </demandValue>
  </demand>
  <demand id="DNVRng_KSCYng">
   <source>DNVRng</source>
   <target>KSCYng</target>
   <demandValue> 21.887720 </demandValue>
  </demand>
  <demand id="DNVRng_LOSAng">
   <source>DNVRng</source>
   <target>LOSAng</target>
   <demandValue> 4.025635 </demandValue>
  </demand>
  <demand id="DNVRng_NYCMng">
   <source>DNVRng</source>
   <target>NYCMng</target>
   <demandValue> 42.993333 </demandValue>
  </demand>
  <demand id="DNVRng_SNVAng">
   <source>DNVRng</source>
   <target>SNVAng</target>
   <demandValue> 8.022984 </demandValue>
  </demand>
  <demand id="DNVRng_STTLng">
   <source>DNVRng</source>
   <target>STTLng</target>
   <demandValue> 8.333088 </demandValue>
  </demand>
  <demand id="DNVRng_WASHng">
   <source>DNVRng</source>
   <target>WASHng</target>
   <demandValue> 32.935384 </demandValue>
  </demand>
  <demand id="HSTNng_ATLAM5">
   <source>HSTNng</source>
   <target>ATLAM5</target>
   <demandValue> 3.297339 </demandValue>
  </demand>
  <demand id="HSTNng_ATLAng">
   <source>HSTNng</source>
   <target>ATLAng</target>
   <demandValue> 6.728261 </demandValue>
  </demand>
  <demand id="HSTNng_CHINng">
   <source>HSTNng</source>
   <target>CHINng</target>
   <demandValue> 15.273797 </demandValue>
  </demand>
  <demand id="HSTNng_DNVRng">
   <source>HSTNng</source>
   <target>DNVRng</target>
   <demandValue> 0.645784 </demandValue>
  </demand>
  <demand id="HSTNng_IPLSng">
   <source>HSTNng</source>
   <target>IPLSng</target>
   <demandValue> 3.970184 </demandValue>
  </demand>
  <demand id="HSTNng_KSCYng">
   <source>HSTNng</source>
   <target>KSCYng</target>
   <demandValue> 1.059125 </demandValue>
  </demand>
  <demand id="HSTNng_LOSAng">
   <source>HSTNng</source>
   <target>LOSAng</target>
   <demandValue> 4.482416 </demandValue>
  </demand>
  <demand id="HSTNng_NYCMng">
   <source>HSTNng</source>
   <target>NYCMng</target>
   <demandValue> 6.365952 </demandValue>
  </demand>
  <demand id="HSTNng_SNVAng">
   <source>HSTNng</source>
   <target>SNVAng</target>
   <demandValue> 0.069787 </demandValue>
  </demand>
  <demand id="HSTNng_STTLng">
   <source>HSTNng</source>
   <target>STTLng</target>
   <demandValue> 1.613787 </demandValue>
  </demand>
  <demand id="HSTNng_WASHng">
   <source>HSTNng</source>
   <target>WASHng</target>
   <demandValue> 4.984949 </demandValue>
  </demand>
  <demand id="IPLSng_ATLAM5">
   <source>IPLSng</source>
   <target>ATLAM5</target>
   <demandValue> 0.026667 </demandValue>
  </demand>
  <demand id="IPLSng_ATLAng">
   <source>IPLSng</source>
   <target>ATLAng</target>
   <demandValue> 16.465248 </demandValue>
  </demand>
  <demand id="IPLSng_CHINng">
   <source>IPLSng</source>
   <target>CHINng</target>
   <demandValue> 73.872211 </demandValue>
  </demand>
  <demand id="IPLSng_DNVRng">
   <source>IPLSng</source>
   <target>DNVRng</target>
   <demandValue> 6.388181 </demandValue>
  </demand>
  <demand id="IPLSng_HSTNng">
   <source>IPLSng</source>
   <target>HSTNng</target>
   <demandValue> 23.047221 </demandValue>
  </demand>
  <demand id="IPLSng_KSCYng">
   <source>IPLSng</source>
   <target>KSCYng</target>
   <demandValue> 2.990453 </demandValue>
  </demand>
  <demand id="IPLSng_LOSAng">
   <source>IPLSng</source>
   <target>LOSAng</target>
   <demandValue> 8.443285 </demandValue>
  </demand>
  <demand id="IPLSng_NYCMng">
   <source>IPLSng</source>
   <target>NYCMng</target>
   <demandValue> 16.190544 </demandValue>
  </demand>
  <demand id="IPLSng_SNVAng">
   <source>IPLSng</source>
   <target>SNVAng</target>
   <demandValue> 0.621845 </demandValue>
  </demand>
  <demand id="IPLSng_STTLng">
   <source>IPLSng</source>
   <target>STTLng</target>
   <demandValue> 18.238515 </demandValue>
  </demand>
  <demand id="IPLSng_WASHng">
   <source>IPLSng</source>
   <target>WASHng</target>
   <demandValue> 14.868547 </demandValue>
  </demand>
  <demand id="KSCYng_ATLAM5">
   <source>KSCYng</source>
   <target>ATLAM5</target>
   <demandValue> 0.365888 </demandValue>
  </demand>
  <demand id="KSCYng_ATLAng">
   <source>KSCYng</source>
   <target>ATLAng</target>
   <demandValue> 5.691469 </demandValue>
  </demand>
  <demand id="KSCYng_CHINng">
   <source>KSCYng</source>
   <target>CHINng</target>
   <demandValue> 17.054595 </demandValue>
  </demand>
  <demand id="KSCYng_DNVRng">
   <source>KSCYng</source>
   <target>DNVRng</target>
   <demandValue> 7.853232 </demandValue>
  </demand>
  <demand id="KSCYng_HSTNng">
   <source>KSCYng</source>
   <target>HSTNng</target>
   <demandValue> 1.169200 </demandValue>
  </demand>
  <demand id="KSCYng_IPLSng">
   <source>KSCYng</source>
   <target>IPLSng</target>
   <demandValue> 13.608104 </demandValue>
  </demand>
  <demand id="KSCYng_LOSAng">
   <source>KSCYng</source>
   <target>LOSAng</target>
   <demandValue> 1.507016 </demandValue>
  </demand>
  <demand id="KSCYng_NYCMng">
   <source>KSCYng</source>
   <target>NYCMng</target>
   <demandValue> 3.453653 </demandValue>
  </demand>
  <demand id="KSCYng_SNVAng">
   <source>KSCYng</source>
   <target>SNVAng</target>
   <demandValue> 2.077005 </demandValue>
  </demand>
  <demand id="KSCYng_STTLng">
   <source>KSCYng</source>
   <target>STTLng</target>
   <demandValue> 4.336616 </demandValue>
  </demand>
  <demand id="KSCYng_WASHng">
   <source>KSCYng</source>
   <target>WASHng</target>
   <demandValue> 28.124448 </demandValue>
  </demand>
  <demand id="LOSAng_ATLAng">
   <source>LOSAng</source>
   <target>ATLAng</target>
   <demandValue> 32.695371 </demandValue>
  </demand>
  <demand id="LOSAng_CHINng">
   <source>LOSAng</source>
   <target>CHINng</target>
   <demandValue> 126.307317 </demandValue>
  </demand>
  <demand id="LOSAng_DNVRng">
   <source>LOSAng</source>
   <target>DNVRng</target>
   <demandValue> 3.996869 </demandValue>
  </demand>
  <demand id="LOSAng_HSTNng">
   <source>LOSAng</source>
   <target>HSTNng</target>
   <demandValue> 18.713704 </demandValue>
  </demand>
  <demand id="LOSAng_IPLSng">
   <source>LOSAng</source>
   <target>IPLSng</target>
   <demandValue> 17.710013 </demandValue>
  </demand>
  <demand id="LOSAng_KSCYng">
   <source>LOSAng</source>
   <target>KSCYng</target>
   <demandValue> 2.737203 </demandValue>
  </demand>
  <demand id="LOSAng_NYCMng">
   <source>LOSAng</source>
   <target>NYCMng</target>
   <demandValue> 52.805341 </demandValue>
  </demand>
  <demand id="LOSAng_SNVAng">
   <source>LOSAng</source>
   <target>SNVAng</target>
   <demandValue> 24.683837 </demandValue>
  </demand>
  <demand id="LOSAng_STTLng">
   <source>LOSAng</source>
   <target>STTLng</target>
   <demandValue> 19.696123 </demandValue>
  </demand>
  <demand id="LOSAng_WASHng">
   <source>LOSAng</source>
   <target>WASHng</target>
   <demandValue> 37.024899 </demandValue>
  </demand>
  <demand id="NYCMng_ATLAM5">
   <source>NYCMng</source>
   <target>ATLAM5</target>
   <demandValue> 0.624160 </demandValue>
  </demand>
  <demand id="NYCMng_ATLAng">
   <source>NYCMng</source>
   <target>ATLAng</target>
   <demandValue> 25.354245 </demandValue>
  </demand>
  <demand id="NYCMng_CHINng">
   <source>NYCMng</source>
   <target>CHINng</target>
   <demandValue> 33.526027 </demandValue>
  </demand>
  <demand id="NYCMng_DNVRng">
   <source>NYCMng</source>
   <target>DNVRng</target>
   <demandValue> 26.734525 </demandValue>
  </demand>
  <demand id="NYCMng_HSTNng">
   <source>NYCMng</source>
   <target>HSTNng</target>
   <demandValue> 6.280099 </demandValue>
  </demand>
  <demand id="NYCMng_IPLSng">
   <source>NYCMng</source>
   <target>IPLSng</target>
   <demandValue> 21.099885 </demandValue>
  </demand>
  <demand id="NYCMng_KSCYng">
   <source>NYCMng</source>
   <target>KSCYng</target>
   <demandValue> 5.877208 </demandValue>
  </demand>
  <demand id="NYCMng_LOSAng">
   <source>NYCMng</source>
   <target>LOSAng</target>
   <demandValue> 63.770747 </demandValue>
  </demand>
  <demand id="NYCMng_SNVAng">
   <source>NYCMng</source>
   <target>SNVAng</target>
   <demandValue> 0.774155 </demandValue>
  </demand>
  <demand id="NYCMng_STTLng">
   <source>NYCMng</source>
   <target>STTLng</target>
   <demandValue> 20.051085 </demandValue>
  </demand>
  <demand id="NYCMng_WASHng">
   <source>NYCMng</source>
   <target>WASHng</target>
   <demandValue> 44.070157 </demandValue>
  </demand>
  <demand id="SNVAng_ATLAng">
   <source>SNVAng</source>
   <target>ATLAng</target>
   <demandValue> 0.087184 </demandValue>
  </demand>
  <demand id="SNVAng_CHINng">
   <source>SNVAng</source>
   <target>CHINng</target>
   <demandValue> 0.080000 </demandValue>
  </demand>
  <demand id="SNVAng_DNVRng">
   <source>SNVAng</source>
   <target>DNVRng</target>
   <demandValue> 3.492787 </demandValue>
  </demand>
  <demand id="SNVAng_HSTNng">
   <source>SNVAng</source>
   <target>HSTNng</target>
   <demandValue> 0.116421 </demandValue>
  </demand>
  <demand id="SNVAng_IPLSng">
   <source>SNVAng</source>
   <target>IPLSng</target>
   <demandValue> 0.268016 </demandValue>
  </demand>
  <demand id="SNVAng_KSCYng">
   <source>SNVAng</source>
   <target>KSCYng</target>
   <demandValue> 0.053333 </demandValue>
  </demand>
  <demand id="SNVAng_LOSAng">
   <source>SNVAng</source>
   <target>LOSAng</target>
   <demandValue> 24.626125 </demandValue>
  </demand>
  <demand id="SNVAng_NYCMng">
   <source>SNVAng</source>
   <target>NYCMng</target>
   <demandValue> 0.287701 </demandValue>
  </demand>
  <demand id="SNVAng_STTLng">
   <source>SNVAng</source>
   <target>STTLng</target>
   <demandValue> 21.751859 </demandValue>
  </demand>
  <demand id="SNVAng_WASHng">
   <source>SNVAng</source>
   <target>WASHng</target>
   <demandValue> 0.026667 </demandValue>
  </demand>
  <demand id="STTLng_ATLAM5">
   <source>STTLng</source>
   <target>ATLAM5</target>
   <demandValue> 0.275984 </demandValue>
  </demand>
  <demand id="STTLng_ATLAng">
   <source>STTLng</source>
   <target>ATLAng</target>
   <demandValue> 9.222773 </demandValue>
  </demand>
  <demand id="STTLng_CHINng">
   <source>STTLng</source>
   <target>CHINng</target>
   <demandValue> 39.488568 </demandValue>
  </demand>
  <demand id="STTLng_DNVRng">
   <source>STTLng</source>
   <target>DNVRng</target>
   <demandValue> 1.369568 </demandValue>
  </demand>
  <demand id="STTLng_HSTNng">
   <source>STTLng</source>
   <target>HSTNng</target>
   <demandValue> 1.095120 </demandValue>
  </demand>
  <demand id="STTLng_IPLSng">
   <source>STTLng</source>
   <target>IPLSng</target>
   <demandValue> 11.105781 </demandValue>
  </demand>
  <demand id="STTLng_KSCYng">
   <source>STTLng</source>
   <target>KSCYng</target>
   <demandValue> 2.037731 </demandValue>
  </demand>
  <demand id="STTLng_LOSAng">
   <source>STTLng</source>
   <target>LOSAng</target>
   <demandValue> 12.832176 </demandValue>
  </demand>
  <demand id="STTLng_NYCMng">
   <source>STTLng</source>
   <target>NYCMng</target>
   <demandValue> 16.961957 </demandValue>
  </demand>
  <demand id="STTLng_SNVAng">
   <source>STTLng</source>
   <target>SNVAng</target>
   <demandValue> 1.810309 </demandValue>
  </demand>
  <demand id="STTLng_WASHng">
   <source>STTLng</source>
   <target>WASHng</target>
   <demandValue> 11.931843 </demandValue>
  </demand>
  <demand id="WASHng_ATLAM5">
   <source>WASHng</source>
   <target>ATLAM5</target>
   <demandValue> 3.924315 </demandValue>
  </demand>
  <demand id="WASHng_ATLAng">
   <source>WASHng</source>
   <target>ATLAng</target>
   <demandValue> 115.563648 </demandValue>
  </demand>
  <demand id="WASHng_CHINng">
   <source>WASHng</source>
   <target>CHINng</target>
   <demandValue> 94.807589 </demandValue>
  </demand>
  <demand id="WASHng_DNVRng">
   <source>WASHng</source>
   <target>DNVRng</target>
   <demandValue> 52.446909 </demandValue>
  </demand>
  <demand id="WASHng_HSTNng">
   <source>WASHng</source>
   <target>HSTNng</target>
   <demandValue> 14.415661 </demandValue>
  </demand>
  <demand id="WASHng_IPLSng">
   <source>WASHng</source>
   <target>IPLSng</target>
   <demandValue> 30.841581 </demandValue>
  </demand>
  <demand id="WASHng_KSCYng">
   <source>WASHng</source>
   <target>KSCYng</target>
   <demandValue> 24.587141 </demandValue>
  </demand>
  <demand id="WASHng_LOSAng">
   <source>WASHng</source>
   <target>LOSAng</target>
   <demandValue> 75.109171 </demandValue>
  </demand>
  <demand id="WASHng_NYCMng">
   <source>WASHng</source>
   <target>NYCMng</target>
   <demandValue> 142.592141 </demandValue>
  </demand>
  <demand id="WASHng_SNVAng">
   <source>WASHng</source>
   <target>SNVAng</target>
   <demandValue> 0.808424 </demandValue>
  </demand>
  <demand id="WASHng_STTLng">
   <source>WASHng</source>
   <target>STTLng</target>
   <demandValue> 42.772643 </demandValue>
  </demand>
 </demands>
</network>